declarative_argparse/__init__.py
declarative_argparse/options/__init__.py
declarative_argparse/options/abc.py
declarative_argparse/options/bool.py
declarative_argparse/options/float.py
declarative_argparse/options/int.py
declarative_argparse/options/path.py
declarative_argparse/options/stores.py
declarative_argparse/options/str.py
declarative_argparse-0.0.8.dist-info/LICENSE
declarative_argparse-0.0.8.dist-info/METADATA
declarative_argparse-0.0.8.dist-info/WHEEL
declarative_argparse-0.0.8.dist-info/RECORD
