Metadata-Version: 2.1
Name: declarative_argparse
Version: 0.0.8
Summary: A simple wrapper around argparse to permit declarative construction and argument retrieval.
Home-page: https://gitlab.com/N3X15/declarative_argparse
Author: Rob Nelson
Author-email: nexisentertainment@gmail.com
Requires-Python: >=3.10,<4.0
Classifier: Programming Language :: Python :: 3
Classifier: Programming Language :: Python :: 3.10
Classifier: Programming Language :: Python :: 3.11
Classifier: Programming Language :: Python :: 3.12
Project-URL: Repository, https://gitlab.com/N3X15/declarative_argparse
